src/create_mcp_server/__init__.py
src/create_mcp_server/__main__.py
src/create_mcp_server/template/README.md.jinja2
src/create_mcp_server/template/__init__.py.jinja2
src/create_mcp_server/template/server.py.jinja2
mseep_create_mcp_server-1.0.6.dev0.dist-info/METADATA
mseep_create_mcp_server-1.0.6.dev0.dist-info/WHEEL
mseep_create_mcp_server-1.0.6.dev0.dist-info/entry_points.txt
mseep_create_mcp_server-1.0.6.dev0.dist-info/licenses/LICENSE
mseep_create_mcp_server-1.0.6.dev0.dist-info/RECORD
