Metadata-Version: 2.4
Name: mseep-create-mcp-server
Version: 1.0.6.dev0
Summary: Create an Model Context Protocol server project from a template.
Project-URL: Homepage, https://modelcontextprotocol.io
Project-URL: Repository, https://github.com/modelcontextprotocol/create-python-server
Author: Anthropic, PBC.
Maintainer-email: David Soria Parra <davidsp@anthropic.com>, Justin Spahr-Summers <justin@anthropic.com>
License: MIT
License-File: LICENSE
Classifier: Development Status :: 4 - Beta
Classifier: Intended Audience :: Developers
Classifier: License :: OSI Approved :: MIT License
Classifier: Programming Language :: Python :: 3
Classifier: Programming Language :: Python :: 3.10
Requires-Python: >=3.10
Requires-Dist: click>=8.1.7
Requires-Dist: jinja2>=3.1.4
Requires-Dist: packaging>=24.2
Requires-Dist: toml>=0.10.2
